package_Andraziel/__init__.py
package_Andraziel/main.py
package_andraziel-0.0.1.dist-info/METADATA
package_andraziel-0.0.1.dist-info/WHEEL
package_andraziel-0.0.1.dist-info/licenses/LICENSE
package_andraziel-0.0.1.dist-info/RECORD
