Metadata-Version: 2.1
Name: package_Andraziel
Version: 0.0.1
Summary: test package
Author-email: Auxence <auxence.deleuziere@isen.yncrea.fr>
License-File: LICENSE
Classifier: License :: OSI Approved :: MIT License
Classifier: Operating System :: OS Independent
Classifier: Programming Language :: Python :: 3
Requires-Python: >=3.7
